README.rst
setup.py
taskcluster_util/__init__.py
taskcluster_util/taskcluster_download.py
taskcluster_util/taskcluster_login.py
taskcluster_util/taskcluster_traverse.py
taskcluster_util/tc_credentials_template.json
taskcluster_util.egg-info/PKG-INFO
taskcluster_util.egg-info/SOURCES.txt
taskcluster_util.egg-info/dependency_links.txt
taskcluster_util.egg-info/entry_points.txt
taskcluster_util.egg-info/not-zip-safe
taskcluster_util.egg-info/pbr.json
taskcluster_util.egg-info/requires.txt
taskcluster_util.egg-info/top_level.txt
taskcluster_util/model/__init__.py
taskcluster_util/model/credentials.py
taskcluster_util/model/login_policy.py
taskcluster_util/util/__init__.py
taskcluster_util/util/downloader.py
taskcluster_util/util/finder.py