Metadata-Version: 1.0
Name: taskcluster-util
Version: 0.0.29
Summary: Taskcluster Utilities
Home-page: https://github.com/askeing/taskcluster-util-python
Author: Askeing Yen
Author-email: askeing@gmail.com
License: UNKNOWN
Keywords: mozilla b2g firefoxos fxos firefox taskcluster utilities download
Platform: UNKNOWN
